pydantic_zarr/__init__.py
pydantic_zarr/_version.py
pydantic_zarr/core.py
pydantic_zarr/py.typed
pydantic_zarr/v2.py
pydantic_zarr/v3.py
pydantic_zarr/experimental/README.md
pydantic_zarr/experimental/__init__.py
pydantic_zarr/experimental/core.py
pydantic_zarr/experimental/v2.py
pydantic_zarr/experimental/v3.py
pydantic_zarr-0.9.1.dist-info/METADATA
pydantic_zarr-0.9.1.dist-info/WHEEL
pydantic_zarr-0.9.1.dist-info/licenses/LICENSE
pydantic_zarr-0.9.1.dist-info/RECORD
