Metadata-Version: 2.4
Name: pydantic-zarr
Version: 0.9.1
Summary: Pydantic models for the Zarr file format
Project-URL: Documentation, https://pydantic-zarr.readthedocs.io/
Project-URL: Issues, https://github.com/zarr-developers/pydantic-zarr/issues
Project-URL: Source, https://github.com/zarr-developers/pydantic-zarr
Author-email: Davis Bennett <davis.v.bennett@gmail.com>
Maintainer: David Stansby
License-Expression: MIT
License-File: LICENSE
Keywords: pydantic,zarr
Classifier: Programming Language :: Python
Classifier: Programming Language :: Python :: 3.11
Classifier: Programming Language :: Python :: 3.12
Classifier: Programming Language :: Python :: Implementation :: CPython
Requires-Python: >=3.11
Requires-Dist: numpy>=1.24.0
Requires-Dist: packaging>=21.0
Requires-Dist: pydantic>2.0.0
Provides-Extra: docs
Requires-Dist: mkdocs-material; extra == 'docs'
Requires-Dist: mkdocstrings[python]; extra == 'docs'
Requires-Dist: pydantic==2.11; extra == 'docs'
Requires-Dist: pytest-examples; extra == 'docs'
Requires-Dist: towncrier; extra == 'docs'
Requires-Dist: zarr>=3.1.0; extra == 'docs'
Provides-Extra: test
Requires-Dist: coverage; extra == 'test'
Requires-Dist: dask==2025.11.0; extra == 'test'
Requires-Dist: pytest-cov; extra == 'test'
Requires-Dist: pytest-examples; extra == 'test'
Requires-Dist: pytest<8.4; extra == 'test'
Requires-Dist: xarray==2025.10.0; extra == 'test'
Requires-Dist: zarr>=3.0.0; extra == 'test'
Provides-Extra: test-base
Requires-Dist: coverage; extra == 'test-base'
Requires-Dist: dask==2025.11.0; extra == 'test-base'
Requires-Dist: pytest-cov; extra == 'test-base'
Requires-Dist: pytest-examples; extra == 'test-base'
Requires-Dist: pytest<8.4; extra == 'test-base'
Requires-Dist: xarray==2025.10.0; extra == 'test-base'
Provides-Extra: zarr
Requires-Dist: zarr>=3.0.0; extra == 'zarr'
